{
  "description" : [
    "An arcade game made for the \"DJ Hero\" turn-table.",
    "You play as a trio of coloured Mayan snakes who must protect the world."
  ],
  "team":{  
    "Art":["Loren Costet", "Antoine Druaux", "Steve Ohl"],
    "Sound":["Antoine Druaux"],
    "Programming":["William Dyce", "Emmanuel Corno"]
  },
  "embed":{
    "youtube":"OTnTjxUkv_k"
  },
  "links":{  
    "GGJ Archive" : "http://archive.globalgamejam.org/2012/quetzalcoatl",
    "Itch.io" : "http://wilbefast.itch.io/dj-quetzal",
    "Indie DB" : "http://www.indiedb.com/games/dj-quetzal-quetzalcoatl",
    "Github" : "https://github.com/wilbefast/quetzalcoatl-game",
    "Montage" : "https://www.youtube.com/watch?v=THmcW-8ll88"
  }
}